README.md
setup.py
twitter_scrape_followers/__init__.py
twitter_scrape_followers.egg-info/PKG-INFO
twitter_scrape_followers.egg-info/SOURCES.txt
twitter_scrape_followers.egg-info/dependency_links.txt
twitter_scrape_followers.egg-info/requires.txt
twitter_scrape_followers.egg-info/top_level.txt